LICENSE
MANIFEST.in
README.md
setup.cfg
setup.py
pycrunch_trace/__init__.py
pycrunch_trace/config.py
pycrunch_trace/demo.py
pycrunch_trace/logging-configuration.yaml
pycrunch_trace/main.py
pycrunch_trace.egg-info/PKG-INFO
pycrunch_trace.egg-info/SOURCES.txt
pycrunch_trace.egg-info/dependency_links.txt
pycrunch_trace.egg-info/not-zip-safe
pycrunch_trace.egg-info/requires.txt
pycrunch_trace.egg-info/top_level.txt
pycrunch_trace/client/__init__.py
pycrunch_trace/client/command_buffer.py
pycrunch_trace/client/api/__init__.py
pycrunch_trace/client/api/network_client.py
pycrunch_trace/client/api/trace.py
pycrunch_trace/client/api/trace_decorator.py
pycrunch_trace/client/api/version.py
pycrunch_trace/client/networking/ClientOutgoingQueueThread.py
pycrunch_trace/client/networking/__init__.py
pycrunch_trace/client/networking/client_trace_introspection.py
pycrunch_trace/client/networking/commands.py
pycrunch_trace/client/networking/strategies/__init__.py
pycrunch_trace/client/networking/strategies/abstract_strategy.py
pycrunch_trace/client/networking/strategies/native_write_strategy.pyx
pycrunch_trace/client/networking/strategies/network_strategy.py
pycrunch_trace/demo/__init__.py
pycrunch_trace/demo/demo_golden.py
pycrunch_trace/demo/demo_million_of_calls.py
pycrunch_trace/demo/demo_no_functon_calls.py
pycrunch_trace/demo/demo_stepping_nested_calls.py
pycrunch_trace/demo/demo_tree_v1.py
pycrunch_trace/demo/demo_with_dict.py
pycrunch_trace/demo/dict_client_demo.py
pycrunch_trace/demo/factorial_demo.py
pycrunch_trace/demo/interactive_demo_01.py
pycrunch_trace/demo/interactive_demo_02.py
pycrunch_trace/demo/interactive_demo_03.py
pycrunch_trace/demo/interactive_demo_04.py
pycrunch_trace/demo/multiple_execution_stack.py
pycrunch_trace/demo/requests_demo.py
pycrunch_trace/demo/timings_demo.py
pycrunch_trace/demo/test_simulated_real/__init__.py
pycrunch_trace/demo/test_simulated_real/test_fact.py
pycrunch_trace/demo/test_simulated_real/test_tree_call_stack_cursors.py
pycrunch_trace/events/__init__.py
pycrunch_trace/events/base_event.py
pycrunch_trace/events/event_buffer_in_protobuf.py
pycrunch_trace/events/file_contents_in_protobuf.pyx
pycrunch_trace/events/method_enter.py
