Metadata-Version: 2.1
Name: pycrunch-trace
Version: 0.3
Summary: PyCrunch Time Travel Debugger
Home-page: https://pytrace.com/
Author: Gleb Sevruk
Author-email: gleb@pycrunch.com
License: MIT
Project-URL: Source, https://github.com/gleb-sevruk/pycrunch-trace/
Project-URL: Funding, https://pycrunch.com/donate
Keywords: tracing,debugging,time-travel debugging,record-and-replay debugging,live coding
Classifier: Development Status :: 3 - Alpha
Classifier: License :: OSI Approved :: MIT License
Classifier: Programming Language :: Python :: 3
Classifier: Topic :: Software Development :: Debuggers
License-File: LICENSE
Requires-Dist: Cython
Requires-Dist: jsonpickle
Requires-Dist: PyYAML
Requires-Dist: protobuf<4,>=3.11.3
